json_types/__init__.py
json_types/py.typed
json_types-0.2.0.dist-info/licenses/LICENSE
json_types-0.2.0.dist-info/WHEEL
json_types-0.2.0.dist-info/METADATA
json_types-0.2.0.dist-info/RECORD
